shadow_data/__init__.py
shadow_data/anonymization.py
shadow_data/cryptohash/__init__.py
shadow_data/cryptohash/symmetric_cipher.py
shadow_data/exceptions.py
shadow_data/l10n/ClearIdentifier.py
shadow_data/l10n/__init__.py
shadow_data/l10n/brazil.py
shadow_data/l10n/usa.py
shadow_data/masking.py
shadow_data/pii/__init__.py
shadow_data/pii/enums.py
shadow_data/pii/spacy.py
shadow_data/reversible.py
shadow_data/utils.py
shadow_data-0.4.1.dist-info/LICENSE
shadow_data-0.4.1.dist-info/METADATA
shadow_data-0.4.1.dist-info/WHEEL
shadow_data-0.4.1.dist-info/RECORD
